README.txt
setup.cfg
setup.py
docs/HISTORY.txt
docs/INSTALL.txt
docs/LICENSE.GPL
docs/LICENSE.txt
pox/__init__.py
pox.banner.egg-info/PKG-INFO
pox.banner.egg-info/SOURCES.txt
pox.banner.egg-info/dependency_links.txt
pox.banner.egg-info/entry_points.txt
pox.banner.egg-info/namespace_packages.txt
pox.banner.egg-info/not-zip-safe
pox.banner.egg-info/paster_plugins.txt
pox.banner.egg-info/requires.txt
pox.banner.egg-info/top_level.txt
pox/banner/README.txt
pox/banner/__init__.py
pox/banner/browser.txt
pox/banner/configure.zcml
pox/banner/interfaces.py
pox/banner/setuphandlers.py
pox/banner/browser/__init__.py
pox/banner/browser/configure.zcml
pox/banner/browser/section.pt
pox/banner/browser/section.py
pox/banner/browser/sectionBanners.py
pox/banner/content/__init__.py
pox/banner/content/banner.py
pox/banner/content/section.py
pox/banner/locales/pox.banner.pot
pox/banner/locales/en/LC_MESSAGES/pox.banner.mo
pox/banner/locales/en/LC_MESSAGES/pox.banner.po
pox/banner/locales/es/LC_MESSAGES/pox.banner.mo
pox/banner/locales/es/LC_MESSAGES/pox.banner.po
pox/banner/profiles/default/catalog.xml
pox/banner/profiles/default/import_steps.xml
pox/banner/profiles/default/pox.banner_various.txt
pox/banner/profiles/default/rolemap.xml
pox/banner/profiles/default/types.xml
pox/banner/profiles/default/workflows.xml
pox/banner/profiles/default/types/Banner.xml
pox/banner/profiles/default/types/Section.xml
pox/banner/profiles/default/workflows/pox.banner_workflow/definition.xml
pox/banner/tests/CreateSectionBanner.conf
pox/banner/tests/__init__.py
pox/banner/tests/test_CreateSectionBanner.py
pox/banner/tests/test_poxbanner.py