Metadata-Version: 1.0
Name: pox.banner
Version: 1.0
Summary: Banners administration for PloneOpenX website
Home-page: http://svn.plone.org/svn/plone/plone.example
Author: Plone Foundation
Author-email: plone-developers@lists.sourceforge.net
License: GPL
Platform: UNKNOWN
Classifier: Framework :: Plone
Classifier: Programming Language :: Python
Classifier: Topic :: Software Development :: Libraries :: Python Modules
